pandas_multiprocess/__init__.py
pandas_multiprocess/multiprocess.py
pandas_multiprocess-0.1.3.dist-info/LICENSE.txt
pandas_multiprocess-0.1.3.dist-info/METADATA
pandas_multiprocess-0.1.3.dist-info/WHEEL
pandas_multiprocess-0.1.3.dist-info/top_level.txt
pandas_multiprocess-0.1.3.dist-info/RECORD
