Metadata-Version: 2.1
Name: pandas-multiprocess
Version: 0.1.3
Summary: Multiprocessing Support for Pandas DataFrame
Home-page: https://github.com/xieqihui/pandas-multiprocess
Author: Qihui Xie
Author-email: xieqihui@gmail.com
Maintainer: Qihui Xie
Maintainer-email: xieqihui@gmail.com
License: LICENSE.txt
Platform: UNKNOWN
Requires-Python: >=2.7
Requires-Dist: numpy
Requires-Dist: pandas
Requires-Dist: tqdm
